poindent/__init__.py
poindent/poindent.py
powrap/__init__.py
powrap/powrap.py
poindent-0.2.0.dist-info/LICENSE
poindent-0.2.0.dist-info/METADATA
poindent-0.2.0.dist-info/WHEEL
poindent-0.2.0.dist-info/entry_points.txt
poindent-0.2.0.dist-info/top_level.txt
poindent-0.2.0.dist-info/RECORD
