Metadata-Version: 2.1
Name: poindent
Version: 0.2.0
Summary: Find an properly reindent .po files.
Home-page: https://github.com/JulienPalard/poindent
Author: Julien Palard
Author-email: julien@palard.fr
License: MIT license
Keywords: poindent
Platform: UNKNOWN
Classifier: Development Status :: 2 - Pre-Alpha
Classifier: Intended Audience :: Developers
Classifier: License :: OSI Approved :: MIT License
Classifier: Natural Language :: English
Classifier: Programming Language :: Python :: 3
Classifier: Programming Language :: Python :: 3.5
Classifier: Programming Language :: Python :: 3.6
Classifier: Programming Language :: Python :: 3.7
Requires-Dist: tqdm
